{
    "juguetes_gatos": [
      {
        "id": 1,
        "nombre": "Juguete de ratón",
        "descripcion": "Juguete interactivo en forma de ratón para entretener a tu gato",
        "precio": 9.99,
        "imagen": "https://www.turacion.com/images/thumbs/0005067_raton-juguete-ferplast_600.jpeg",
        "reviews":23
      },
      {
        "id": 2,
        "nombre": "Pelotas de colores",
        "descripcion": "Set de pelotas de colores brillantes para jugar y ejercitar a tu gato",
        "precio": 7.99,
        "imagen": "https://encrypted-tbn0.gstatic.com/images?q=tbn:ANd9GcTSesBgdM9hHDfFLP2lUdg88FIww2XbtqUMPIj0DPKj0G0UlasPX_bJdFkgYdgY9gZRnMI&usqp=CAU",
        "reviews":28        
      },
      {
        "id": 3,
        "nombre": "Caña con plumas",
        "descripcion": "Caña de pescar con plumas para estimular el instinto de caza de tu gato",
        "precio": 12.99,
        "imagen": "https://www.agropecuariaagraciada.com.uy/wp-content/uploads/2022/08/WhatsApp-Image-2023-01-03-at-13.20.58.jpeg",
        "reviews":19
      },
      {
        "id": 4,
        "nombre": "Túnel de juego",
        "descripcion": "Túnel plegable para que tu gato se divierta correteando y escondiéndose",
        "precio": 19.99,
        "imagen": "https://gatificando.com/wp-content/uploads/tunel-gatificando-gatos.jpg",
        "reviews":21
      },
      {
        "id": 5,
        "nombre": "Peluche interactivo",
        "descripcion": "Peluche que emite sonidos al ser presionado para estimular a tu gato",
        "precio": 14.99,
        "imagen": "https://prod-resize.tiendainglesa.com.uy/images/medium/P551010-1.jpg?20230523130021,Gato-de-Peluche-con-Sonido-PHI-PHI-TOYS-30-cm-en-Tienda-Inglesa",
        "reviews":12
      },
      {
        "id": 6,
        "nombre": "Cañita con cascabeles",
        "descripcion": "Caña con cascabeles para jugar y compartir momentos divertidos con tu gato",
        "precio": 8.99,
        "imagen": "https://goldpet.es/82452-large_default/baston-con-muneco-y-cascabel-para-gatos-ferribiella.jpg",
        "reviews":31
      },
      {
        "id": 7,
        "nombre": "Bolas de lana",
        "descripcion": "Bolas suaves de lana para que tu gato juegue y las persiga",
        "precio": 6.99,
        "imagen": "https://m.media-amazon.com/images/I/71Mw7z1SamL.jpg",
        "reviews":25
      },
      {
        "id": 8,
        "nombre": "Juguete de plumas",
        "descripcion": "Varita con plumas para despertar el instinto cazador de tu gato",
        "precio": 10.99,
        "imagen": "https://www.americanpet.com.uy/images/virtuemart/product/resized/ME6113_640x640.jpg",
        "reviews":23
      },
      {
        "id": 9,
        "nombre": "Laberinto de bolas",
        "descripcion": "Juguete con bolas en un laberinto para mantener entretenido a tu gato",
        "precio": 24.99,
        "imagen": "https://cdn.manomano.com/images/images_products/30054873/P/93364799_1.jpg",
        "reviews":27
      },
      {
        "id": 10,
        "nombre": "Ratón electrónico",
        "descripcion": "Ratón electrónico que se mueve para estimular la curiosidad de tu gato",
        "precio": 17.99,
        "imagen": "https://f.fcdn.app/imgs/331aca/www.elcapitan.com.uy/capiuy/f258/original/catalogo/DGS-PET2204-11_DGS-PET2204-11_4/2000-2000/raton-control-remoto-juguete-gatos-raton-control-remoto-juguete-gatos.jpg",
        "reviews":44
      }
    ]
  }